randomquotes.py
randomquotes-1.0.dist-info/METADATA
randomquotes-1.0.dist-info/WHEEL
randomquotes-1.0.dist-info/top_level.txt
randomquotes-1.0.dist-info/RECORD
