Metadata-Version: 2.1
Name: randomquotes
Version: 1.0
Summary: A package that generates quotes of life and smile 
Home-page: https://github.com/kaviyasobanbabu/randomquotes.git
Author: kaviya P S, venkateswar.S
Author-email: kaviyasobanbabu@gmail.com
License: UNKNOWN
Platform: UNKNOWN
Classifier: Programming Language :: Python :: 3.5
Classifier: Programming Language :: Python :: 3.6
Classifier: Programming Language :: Python :: 3.7
Classifier: Programming Language :: Python :: 3.8
Classifier: Operating System :: OS Independent
Requires-Dist: random
